invrcpt/__init__.py
invrcpt/exporter.py
invrcptexporter-0.3.1.dist-info/DESCRIPTION.rst
invrcptexporter-0.3.1.dist-info/METADATA
invrcptexporter-0.3.1.dist-info/RECORD
invrcptexporter-0.3.1.dist-info/WHEEL
invrcptexporter-0.3.1.dist-info/metadata.json
invrcptexporter-0.3.1.dist-info/top_level.txt
