Metadata-Version: 2.0
Name: invrcptexporter
Version: 0.3.1
Summary: a tool to export invoice and receipt fromlibreoffice calc into pdf file 
Home-page: https://github.com/pchaitat/invrcptexporter
Author: pchaitat
Author-email: chaitat@the-im.com
License: GPL-3.0
Keywords: libreoffice libreoffice-calc python python-uno invoice-generator
Platform: UNKNOWN
Classifier: Development Status :: 3 - Alpha
Classifier: Intended Audience :: Developers
Classifier: Topic :: Office/Business :: Financial :: Spreadsheet
Classifier: License :: OSI Approved :: GNU General Public License v3 (GPLv3)
Classifier: Programming Language :: Python :: 3.4
